{
  "run_id": "product-service_h1_spike_rep1",
  "service": "product-service",
  "config": "h1",
  "pattern": "spike",
  "repetition": 1,
  "start_epoch": 1776165578,
  "end_epoch": 1776166902,
  "duration_seconds": 1324,
  "k6_job_name": "k6-load-test-spike-product-service-h1-spike-rep1",
  "target_url": "http://product-service.ecommerce.svc.cluster.local:8002",
  "load_profile": {
    "version": "recovery-v2",
    "base_rps": 20,
    "peak_rps": 200,
    "page_size": 100,
    "max_page": 12,
    "search_terms": "Laptop,Phone,Camera,Headphones,Keyboard,Monitor,Speaker,Charger"
  },
  "timestamp": "2026-04-14T11:41:42+00:00"
}
